gaea/__init__.py
gaea/__web__/__init__.py
gaea/__web__/static/icon.gif
gaea/__web__/templates/index.html
gaea/digitalocean.py
gaea/dynadot.py
libgaea-0.0.41.dist-info/entry_points.txt
libgaea-0.0.41.dist-info/LICENSE
libgaea-0.0.41.dist-info/WHEEL
libgaea-0.0.41.dist-info/METADATA
libgaea-0.0.41.dist-info/RECORD
